{
  "exportedAt": "09/04/2026 12:43:02 AM",
  "groupId": "27146517294939727",
  "groupName": "ফরেক্স ট্রেডার কমিউনিটি",
  "totalMembers": 211,
  "members": [
    {
      "id": "581210659"
    },
    {
      "id": "1093351974"
    },
    {
      "id": "1363359446"
    },
    {
      "id": "1392366144"
    },
    {
      "id": "1550824578"
    },
    {
      "id": "1551553462"
    },
    {
      "id": "1692984375"
    },
    {
      "id": "61550870316257"
    },
    {
      "id": "61551614861303"
    },
    {
      "id": "61552297198079"
    },
    {
      "id": "61553618794289"
    },
    {
      "id": "61554027984487"
    },
    {
      "id": "61558978906801"
    },
    {
      "id": "61559064847026"
    },
    {
      "id": "61559845840409"
    },
    {
      "id": "61559849760741"
    },
    {
      "id": "61559854196511"
    },
    {
      "id": "61564014137380"
    },
    {
      "id": "61565307150484"
    },
    {
      "id": "61572367827101"
    },
    {
      "id": "61574050941300"
    },
    {
      "id": "61576179002240"
    },
    {
      "id": "61576697524876"
    },
    {
      "id": "61577812619230"
    },
    {
      "id": "61578304126152"
    },
    {
      "id": "61578887886626"
    },
    {
      "id": "61582183760025"
    },
    {
      "id": "61582357813298"
    },
    {
      "id": "61583346486361"
    },
    {
      "id": "61583894103477"
    },
    {
      "id": "61585894162813"
    },
    {
      "id": "100000073301860"
    },
    {
      "id": "100000132868009"
    },
    {
      "id": "100000414635770"
    },
    {
      "id": "100000514684386"
    },
    {
      "id": "100000933754971"
    },
    {
      "id": "100001295106498"
    },
    {
      "id": "100001680168938"
    },
    {
      "id": "100001839318456"
    },
    {
      "id": "100001956390827"
    },
    {
      "id": "100002144788724"
    },
    {
      "id": "100002180826206"
    },
    {
      "id": "100002207771257"
    },
    {
      "id": "100002306461316"
    },
    {
      "id": "100002330610799"
    },
    {
      "id": "100002579698284"
    },
    {
      "id": "100002760241553"
    },
    {
      "id": "100002771053061"
    },
    {
      "id": "100003213452551"
    },
    {
      "id": "100003447655302"
    },
    {
      "id": "100003490405588"
    },
    {
      "id": "100003550691669"
    },
    {
      "id": "100003577860161"
    },
    {
      "id": "100003579826952"
    },
    {
      "id": "100003671197131"
    },
    {
      "id": "100004066506000"
    },
    {
      "id": "100004152810820"
    },
    {
      "id": "100004401468872"
    },
    {
      "id": "100004408570740"
    },
    {
      "id": "100004624506695"
    },
    {
      "id": "100005151197992"
    },
    {
      "id": "100005581440907"
    },
    {
      "id": "100006338526744"
    },
    {
      "id": "100006557675769"
    },
    {
      "id": "100006734321559"
    },
    {
      "id": "100006961535787"
    },
    {
      "id": "100007003966302"
    },
    {
      "id": "100007184684644"
    },
    {
      "id": "100007222447418"
    },
    {
      "id": "100007736807668"
    },
    {
      "id": "100007888895791"
    },
    {
      "id": "100007908810016"
    },
    {
      "id": "100007954038179"
    },
    {
      "id": "100007970771421"
    },
    {
      "id": "100008016691205"
    },
    {
      "id": "100008122669389"
    },
    {
      "id": "100008276773138"
    },
    {
      "id": "100008446090941"
    },
    {
      "id": "100008721577490"
    },
    {
      "id": "100009050504814"
    },
    {
      "id": "100009219731268"
    },
    {
      "id": "100009631755899"
    },
    {
      "id": "100009678482759"
    },
    {
      "id": "100009940381279"
    },
    {
      "id": "100009953084747"
    },
    {
      "id": "100010061352913"
    },
    {
      "id": "100010211890542"
    },
    {
      "id": "100010310566232"
    },
    {
      "id": "100010522593963"
    },
    {
      "id": "100010570626498"
    },
    {
      "id": "100011072148420"
    },
    {
      "id": "100011090865119"
    },
    {
      "id": "100011184520179"
    },
    {
      "id": "100012179984918"
    },
    {
      "id": "100012322898296"
    },
    {
      "id": "100012449863610"
    },
    {
      "id": "100012714856351"
    },
    {
      "id": "100012873075963"
    },
    {
      "id": "100013003771676"
    },
    {
      "id": "100013074793680"
    },
    {
      "id": "100014395182921"
    },
    {
      "id": "100014575509797"
    },
    {
      "id": "100014698988973"
    },
    {
      "id": "100014847276879"
    },
    {
      "id": "100015094785573"
    },
    {
      "id": "100015297163446"
    },
    {
      "id": "100015556530232"
    },
    {
      "id": "100015560986926"
    },
    {
      "id": "100015630340542"
    },
    {
      "id": "100015651015759"
    },
    {
      "id": "100016006053036"
    },
    {
      "id": "100016309183016"
    },
    {
      "id": "100016321386384"
    },
    {
      "id": "100016500212019"
    },
    {
      "id": "100016875194742"
    },
    {
      "id": "100019843841106"
    },
    {
      "id": "100020141395731"
    },
    {
      "id": "100020310739054"
    },
    {
      "id": "100021003364949"
    },
    {
      "id": "100021437530257"
    },
    {
      "id": "100021893438874"
    },
    {
      "id": "100021931390252"
    },
    {
      "id": "100022209471173"
    },
    {
      "id": "100023537912174"
    },
    {
      "id": "100023797150529"
    },
    {
      "id": "100024009123750"
    },
    {
      "id": "100024151762500"
    },
    {
      "id": "100024739205637"
    },
    {
      "id": "100027342244758"
    },
    {
      "id": "100028619054693"
    },
    {
      "id": "100028637782880"
    },
    {
      "id": "100031240473220"
    },
    {
      "id": "100033577763209"
    },
    {
      "id": "100034200248609"
    },
    {
      "id": "100034717232439"
    },
    {
      "id": "100035100939774"
    },
    {
      "id": "100035298752480"
    },
    {
      "id": "100035837195457"
    },
    {
      "id": "100036867196696"
    },
    {
      "id": "100037083272225"
    },
    {
      "id": "100037283285894"
    },
    {
      "id": "100037327150296"
    },
    {
      "id": "100037949257592"
    },
    {
      "id": "100039159099456"
    },
    {
      "id": "100039217021433"
    },
    {
      "id": "100040677093627"
    },
    {
      "id": "100041326611682"
    },
    {
      "id": "100041474234755"
    },
    {
      "id": "100042032738869"
    },
    {
      "id": "100043534997738"
    },
    {
      "id": "100046305294366"
    },
    {
      "id": "100046430658726"
    },
    {
      "id": "100048628372642"
    },
    {
      "id": "100049146600404"
    },
    {
      "id": "100050236449804"
    },
    {
      "id": "100050241020237"
    },
    {
      "id": "100051379062018"
    },
    {
      "id": "100052015964381"
    },
    {
      "id": "100052333590059"
    },
    {
      "id": "100052979541747"
    },
    {
      "id": "100053437385044"
    },
    {
      "id": "100053960433663"
    },
    {
      "id": "100054208539599"
    },
    {
      "id": "100057135216996"
    },
    {
      "id": "100057158711272"
    },
    {
      "id": "100057650234267"
    },
    {
      "id": "100059133233370"
    },
    {
      "id": "100062206564834"
    },
    {
      "id": "100062405635265"
    },
    {
      "id": "100063548623544"
    },
    {
      "id": "100064646495911"
    },
    {
      "id": "100064688599359"
    },
    {
      "id": "100066227952807"
    },
    {
      "id": "100066506385533"
    },
    {
      "id": "100069602563686"
    },
    {
      "id": "100071119163206"
    },
    {
      "id": "100071647812983"
    },
    {
      "id": "100072257783888"
    },
    {
      "id": "100073092190864"
    },
    {
      "id": "100073283154433"
    },
    {
      "id": "100073893893067"
    },
    {
      "id": "100076310496282"
    },
    {
      "id": "100076652730926"
    },
    {
      "id": "100077682617092"
    },
    {
      "id": "100077983816270"
    },
    {
      "id": "100078694557755"
    },
    {
      "id": "100078842378044"
    },
    {
      "id": "100079217002912"
    },
    {
      "id": "100080168883357"
    },
    {
      "id": "100081563677035"
    },
    {
      "id": "100082132784655"
    },
    {
      "id": "100082819727698"
    },
    {
      "id": "100083158934821"
    },
    {
      "id": "100084504040816"
    },
    {
      "id": "100085325029407"
    },
    {
      "id": "100085889678624"
    },
    {
      "id": "100086673139149"
    },
    {
      "id": "100086924863322"
    },
    {
      "id": "100088180724115"
    },
    {
      "id": "100088733397755"
    },
    {
      "id": "100090526045456"
    },
    {
      "id": "100091963416217"
    },
    {
      "id": "100092129364471"
    },
    {
      "id": "100092333055628"
    },
    {
      "id": "100092698540228"
    },
    {
      "id": "100093166878624"
    },
    {
      "id": "100093232357669"
    },
    {
      "id": "100093885916667"
    },
    {
      "id": "100094440370437"
    },
    {
      "id": "100094464008191"
    },
    {
      "id": "100094559312444"
    }
  ]
}